geoRDDprep/__init__.py
geoRDDprep/main.py
georddprep-0.1.2.dist-info/METADATA
georddprep-0.1.2.dist-info/WHEEL
georddprep-0.1.2.dist-info/top_level.txt
georddprep-0.1.2.dist-info/RECORD
