Metadata-Version: 2.4
Name: geoRDDprep
Version: 0.1.2
Summary: Preparing data for regression discontinuity design
Home-page: https://github.com/shahirshamim/geoRDDprep
Author: Shahir Shamim
Author-email: shahir15314@gmail.com
Keywords: python,regression,discontinuity,geographic,spatial,gis
Classifier: Development Status :: 3 - Alpha
Classifier: Intended Audience :: Developers
Classifier: Intended Audience :: Science/Research
Classifier: Programming Language :: Python :: 3
Classifier: License :: OSI Approved :: MIT License
Classifier: Operating System :: OS Independent
Requires-Python: >=3.6
Requires-Dist: geopandas
Requires-Dist: numpy
Requires-Dist: pandas
Requires-Dist: shapely
Requires-Dist: scipy
Dynamic: author
Dynamic: author-email
Dynamic: classifier
Dynamic: description
Dynamic: description-content-type
Dynamic: home-page
Dynamic: keywords
Dynamic: requires-dist
Dynamic: requires-python
Dynamic: summary
